douban_crack/__about__.py
douban_crack/__init__.py
douban_crack/py.typed
douban_crack/crack_data/crack_data.py
douban_crack/crack_data/feross.buffer.6.0.3.js
douban_crack/crack_data/index.html
douban_crack/crack_data/index.js
douban_crack/crack_data/main.js
douban_crack/crack_data/xxhash.min.js
douban_crack/crack_html/crack_html.py
douban_crack-0.0.2.dist-info/METADATA
douban_crack-0.0.2.dist-info/WHEEL
douban_crack-0.0.2.dist-info/licenses/LICENSE
douban_crack-0.0.2.dist-info/RECORD
